LICENSE
README.md
setup.py
pyBarSim.egg-info/PKG-INFO
pyBarSim.egg-info/SOURCES.txt
pyBarSim.egg-info/dependency_links.txt
pyBarSim.egg-info/requires.txt
pyBarSim.egg-info/top_level.txt
pybarsim/__init__.py
pybarsim/barsim.py