Metadata-Version: 2.1
Name: pyBarSim
Version: 0.1.0
Summary: Python package to simulate wave-dominated shallow-marine environments
Home-page: https://github.com/grongier/pybarsim
Author: Guillaume Rongier
License: MIT
Project-URL: Reference, https://doi.org/10.1016/S0025-3227(03)00144-0
Project-URL: Source, https://github.com/grongier/pybarsim
Keywords: stratigraphic modeling,shallow-marine,event-based
Classifier: Development Status :: 4 - Beta
Classifier: Intended Audience :: Developers
Classifier: Topic :: Scientific/Engineering
Classifier: Topic :: Software Development :: Libraries
Classifier: Topic :: Software Development :: Libraries :: Python Modules
Classifier: License :: OSI Approved :: MIT License
Classifier: Programming Language :: Python :: 3
Classifier: Programming Language :: Python :: 3.7
Requires-Python: >=3.7
License-File: LICENSE
Requires-Dist: numpy
Requires-Dist: scipy
Requires-Dist: numba
Requires-Dist: xarray
Requires-Dist: matplotlib
